ObjectFinder/ObjectFinder.py
ObjectFinder/__init__.py
objectfinder-0.0.1.dist-info/METADATA
objectfinder-0.0.1.dist-info/WHEEL
objectfinder-0.0.1.dist-info/top_level.txt
objectfinder-0.0.1.dist-info/RECORD
