Metadata-Version: 2.1
Name: objectfinder
Version: 0.0.1
Summary: a package to help generate skew for celestial objects
